Metadata-Version: 2.1
Name: odoo12-addon-delivery-seur
Version: 12.0.1.1.6
Summary: Integrate SEUR webservice
Home-page: https://github.com/OCA/l10n-spain
Author: Trey (www.trey.es), FactorLibre, Odoo Community Association (OCA)
Author-email: support@odoo-community.org
License: AGPL-3
Platform: UNKNOWN
Classifier: Programming Language :: Python
Classifier: Framework :: Odoo
Classifier: Framework :: Odoo :: 12.0
Classifier: License :: OSI Approved :: GNU Affero General Public License v3
Requires-Python: >=3.5
Requires-Dist: odoo12-addon-delivery-package-number
Requires-Dist: odoo12-addon-delivery-price-method
Requires-Dist: odoo12-addon-delivery-state
Requires-Dist: odoo (<12.1dev,>=12.0a)
Requires-Dist: zeep
